{
  "profession": "mechanical_engineer",
  "locale": "ar",
  "experience_bullets": [
    "نفذت المبادرات الاستراتيجية مع تقليل الأخطاء بنسبة 28%.",
    "أدرت علاقات العملاء بمعدل نجاح وصل إلى 98%.",
    "حللت مخرجات المشروع مع تقليل الأخطاء بنسبة 25%.",
    "حسنت علاقات العملاء لأكثر من 35 عميل.",
    "نفذت سير عمل الفريق لأكثر من 29 عميل.",
    "يسّرت سير عمل الفريق لأكثر من 50 عميل.",
    "حسنت تحسينات العمليات مع تقليل الأخطاء بنسبة 23%.",
    "حللت سير عمل الفريق مع تقليل الأخطاء بنسبة 27%.",
    "قدت سير عمل الفريق لأكثر من 26 عميل.",
    "يسّرت علاقات العملاء مما وفر 48 ألف دولار سنوياً.",
    "قدت تحسينات العمليات بميزانية تجاوزت 4 مليون.",
    "حسنت تحسينات العمليات مما وفر 33 ألف دولار سنوياً.",
    "قدت علاقات العملاء لأكثر من 48 عميل.",
    "قدت تحليل البيانات مع تقليل الأخطاء بنسبة 25%.",
    "أدرت تحليل البيانات بميزانية تجاوزت 2 مليون.",
    "أدرت تحليل البيانات مع تقليل الأخطاء بنسبة 27%.",
    "حللت تحليل البيانات بميزانية تجاوزت 4 مليون.",
    "أدرت تحليل البيانات مع تقليل الأخطاء بنسبة 29%.",
    "طبقت ضمان الجودة مما وفر 19 ألف دولار سنوياً.",
    "أدرت سير عمل الفريق بمعدل نجاح وصل إلى 90%.",
    "حللت علاقات العملاء مما وفر 47 ألف دولار سنوياً.",
    "نسقت علاقات العملاء مع تقليل الأخطاء بنسبة 23%.",
    "نسقت سير عمل الفريق بمعدل نجاح وصل إلى 94%.",
    "نفذت تحليل البيانات بنسبة 32%.",
    "نفذت تحسينات العمليات مع زيادة الكفاءة بنسبة 37%.",
    "حللت سير عمل الفريق مما وفر 28 ألف دولار سنوياً.",
    "طبقت تحليل البيانات بميزانية تجاوزت 5 مليون.",
    "نسقت سير عمل الفريق مما وفر 57 ألف دولار سنوياً.",
    "طبقت تحسينات العمليات بمعدل نجاح وصل إلى 97%.",
    "حللت مخرجات المشروع مع تقليل الأخطاء بنسبة 19%."
  ],
  "project_examples": [
    {
      "name": "إعادة التنظيم الإداري",
      "description": "إجراء دورات تدريبية للموظفين.",
      "tech": "التحليلات, التخطيط, التواصل"
    },
    {
      "name": "إعادة التنظيم الإداري",
      "description": "إجراء دورات تدريبية للموظفين.",
      "tech": "القيادة, التخطيط, التواصل"
    },
    {
      "name": "تنفيذ البرمجيات",
      "description": "إجراء دورات تدريبية للموظفين.",
      "tech": "العمليات, تصور البيانات, أوفيس"
    },
    {
      "name": "إصلاح توجيه العملاء",
      "description": "التعاون مع أصحاب المصلحة لتحديد المتطلبات.",
      "tech": "أوفيس, التحليلات, برامج إدارة المشاريع"
    },
    {
      "name": "إصلاح توجيه العملاء",
      "description": "مراقبة المقاييس والإبلاغ عن مؤشرات الأداء.",
      "tech": "إدارة المخاطر, العمليات, التواصل"
    },
    {
      "name": "تحسين العمليات",
      "description": "التعاون مع أصحاب المصلحة لتحديد المتطلبات.",
      "tech": "تصور البيانات, أنظمة إدارة العلاقات, إدارة المخاطر"
    },
    {
      "name": "تنفيذ البرمجيات",
      "description": "مراقبة المقاييس والإبلاغ عن مؤشرات الأداء.",
      "tech": "أنظمة إدارة العلاقات, التحليلات, إدارة المخاطر"
    },
    {
      "name": "تحسين العمليات",
      "description": "التعاون مع أصحاب المصلحة لتحديد المتطلبات.",
      "tech": "القيادة, تصور البيانات, إدارة المخاطر"
    },
    {
      "name": "إعادة التنظيم الإداري",
      "description": "التعاون مع أصحاب المصلحة لتحديد المتطلبات.",
      "tech": "أنظمة إدارة العلاقات, التواصل, تصور البيانات"
    },
    {
      "name": "تحسين العمليات",
      "description": "التعاون مع أصحاب المصلحة لتحديد المتطلبات.",
      "tech": "إدارة المخاطر, العمليات, أنظمة إدارة العلاقات"
    },
    {
      "name": "إعادة التنظيم الإداري",
      "description": "إجراء دورات تدريبية للموظفين.",
      "tech": "العمليات, تصور البيانات, التواصل"
    },
    {
      "name": "تنفيذ البرمجيات",
      "description": "تسليم المشروع بنجاح قبل الموعد المحدد.",
      "tech": "أوفيس, التحليلات, التخطيط"
    },
    {
      "name": "تحسين العمليات",
      "description": "التعاون مع أصحاب المصلحة لتحديد المتطلبات.",
      "tech": "التواصل, برامج إدارة المشاريع, أوفيس"
    },
    {
      "name": "إعادة التنظيم الإداري",
      "description": "مراقبة المقاييس والإبلاغ عن مؤشرات الأداء.",
      "tech": "التحليلات, أوفيس, العمليات"
    },
    {
      "name": "إصلاح توجيه العملاء",
      "description": "تسليم المشروع بنجاح قبل الموعد المحدد.",
      "tech": "إدارة المخاطر, التخطيط, أنظمة إدارة العلاقات"
    },
    {
      "name": "تحسين العمليات",
      "description": "مراقبة المقاييس والإبلاغ عن مؤشرات الأداء.",
      "tech": "أوفيس, برامج إدارة المشاريع, العمليات"
    },
    {
      "name": "تحسين العمليات",
      "description": "مراقبة المقاييس والإبلاغ عن مؤشرات الأداء.",
      "tech": "برامج إدارة المشاريع, تصور البيانات, القيادة"
    },
    {
      "name": "تحسين العمليات",
      "description": "إجراء دورات تدريبية للموظفين.",
      "tech": "تصور البيانات, القيادة, برامج إدارة المشاريع"
    },
    {
      "name": "إصلاح توجيه العملاء",
      "description": "التعاون مع أصحاب المصلحة لتحديد المتطلبات.",
      "tech": "برامج إدارة المشاريع, أنظمة إدارة العلاقات, التخطيط"
    },
    {
      "name": "إصلاح توجيه العملاء",
      "description": "إجراء دورات تدريبية للموظفين.",
      "tech": "التحليلات, التخطيط, إدارة المخاطر"
    }
  ],
  "soft_skills": [
    "القدرة على التكيف",
    "القيادة",
    "القدرة على التكيف",
    "حل المشكلات",
    "العمل الجماعي",
    "حل المشكلات",
    "التفكير النقدي",
    "القيادة",
    "العمل الجماعي",
    "العمل الجماعي",
    "العمل الجماعي",
    "القدرة على التكيف",
    "التواصل",
    "العمل الجماعي",
    "التفكير النقدي"
  ],
  "achievements": [
    "تم التكريم للأداء المتميز، مما أدى إلى تحسين المقاييس الرئيسية بميزانية تجاوزت 2 مليون.",
    "تم التكريم للأداء المتميز، مما أدى إلى تحسين المقاييس الرئيسية بنسبة 27%.",
    "تم التكريم للأداء المتميز، مما أدى إلى تحسين المقاييس الرئيسية مع زيادة الكفاءة بنسبة 23%.",
    "تم التكريم للأداء المتميز، مما أدى إلى تحسين المقاييس الرئيسية مع تقليل الأخطاء بنسبة 24%.",
    "تم التكريم للأداء المتميز، مما أدى إلى تحسين المقاييس الرئيسية مع زيادة الكفاءة بنسبة 28%.",
    "تم التكريم للأداء المتميز، مما أدى إلى تحسين المقاييس الرئيسية لأكثر من 31 عميل.",
    "تم التكريم للأداء المتميز، مما أدى إلى تحسين المقاييس الرئيسية مع تقليل الأخطاء بنسبة 23%.",
    "تم التكريم للأداء المتميز، مما أدى إلى تحسين المقاييس الرئيسية مع زيادة الكفاءة بنسبة 37%.",
    "تم التكريم للأداء المتميز، مما أدى إلى تحسين المقاييس الرئيسية مع تقليل الأخطاء بنسبة 27%.",
    "تم التكريم للأداء المتميز، مما أدى إلى تحسين المقاييس الرئيسية بمعدل نجاح وصل إلى 99%.",
    "تم التكريم للأداء المتميز، مما أدى إلى تحسين المقاييس الرئيسية مع تقليل الأخطاء بنسبة 17%.",
    "تم التكريم للأداء المتميز، مما أدى إلى تحسين المقاييس الرئيسية بمعدل نجاح وصل إلى 97%.",
    "تم التكريم للأداء المتميز، مما أدى إلى تحسين المقاييس الرئيسية بمعدل نجاح وصل إلى 90%.",
    "تم التكريم للأداء المتميز، مما أدى إلى تحسين المقاييس الرئيسية مع تقليل الأخطاء بنسبة 23%.",
    "تم التكريم للأداء المتميز، مما أدى إلى تحسين المقاييس الرئيسية بنسبة 20%."
  ],
  "certifications": [
    "تدريب على القيادة - متقدم",
    "شهادة سلامة متقدمة",
    "شهادة معتمدة في الصناعة",
    "رخصة مهنية - متقدم",
    "شهادة سلامة متقدمة",
    "رخصة مهنية",
    "رخصة مهنية - متقدم",
    "تدريب على القيادة",
    "رخصة مهنية",
    "تدريب على القيادة - متقدم",
    "تدريب على القيادة",
    "شهادة معتمدة في الصناعة",
    "تدريب على القيادة - متقدم",
    "تدريب على القيادة",
    "رخصة مهنية"
  ],
  "career_objectives": [
    "استغلال خبرتي في التخطيط والعمل الجماعي لتقديم قيمة مضافة وتحقيق النمو.",
    "استغلال خبرتي في أوفيس والقيادة لتقديم قيمة مضافة وتحقيق النمو.",
    "استغلال خبرتي في التخطيط والعمل الجماعي لتقديم قيمة مضافة وتحقيق النمو.",
    "استغلال خبرتي في إدارة المخاطر والتواصل لتقديم قيمة مضافة وتحقيق النمو.",
    "استغلال خبرتي في العمليات والعمل الجماعي لتقديم قيمة مضافة وتحقيق النمو.",
    "استغلال خبرتي في برامج إدارة المشاريع والتفكير النقدي لتقديم قيمة مضافة وتحقيق النمو.",
    "استغلال خبرتي في إدارة المخاطر والقدرة على التكيف لتقديم قيمة مضافة وتحقيق النمو.",
    "استغلال خبرتي في إدارة المخاطر والقدرة على التكيف لتقديم قيمة مضافة وتحقيق النمو.",
    "استغلال خبرتي في تصور البيانات والتفكير النقدي لتقديم قيمة مضافة وتحقيق النمو.",
    "استغلال خبرتي في القيادة وحل المشكلات لتقديم قيمة مضافة وتحقيق النمو."
  ],
  "keywords": [
    "تصور البيانات",
    "التحليلات",
    "أجايل",
    "أوفيس",
    "التحليلات",
    "العمل الجماعي",
    "التفكير النقدي",
    "التواصل",
    "حل المشكلات",
    "التواصل",
    "أنظمة إدارة العلاقات",
    "إدارة المخاطر",
    "إدارة الوقت",
    "تصور البيانات",
    "أجايل",
    "التحليلات",
    "أجايل",
    "التخطيط",
    "التواصل",
    "القيادة"
  ]
}